examples/basic_usage.py
phydroperiod/__init__.py
phydroperiod/core.py
phydroperiod-0.1.3.dist-info/licenses/LICENSE
tests/__init__.py
tests/test_core.py
phydroperiod-0.1.3.dist-info/METADATA
phydroperiod-0.1.3.dist-info/WHEEL
phydroperiod-0.1.3.dist-info/entry_points.txt
phydroperiod-0.1.3.dist-info/top_level.txt
phydroperiod-0.1.3.dist-info/RECORD
