Metadata-Version: 2.4
Name: phydroperiod
Version: 0.1.3
Summary: Cálculo de hidroperiodo a partir de máscaras de agua
Author-email: "Diego García Díaz, Javier Bustamante Díaz" <diegogarcia@ebd.csic.es>
License: MIT
Project-URL: Homepage, https://github.com/Digdgeo/Phydroperiod
Project-URL: Repository, https://github.com/Digdgeo/Phydroperiod
Project-URL: Issues, https://github.com/Digdgeo/Phydroperiod/issues
Keywords: hydroperiod,remote-sensing,wetlands,hydrology,GIS
Classifier: Development Status :: 3 - Alpha
Classifier: Intended Audience :: Science/Research
Classifier: License :: OSI Approved :: MIT License
Classifier: Operating System :: OS Independent
Classifier: Programming Language :: Python :: 3
Classifier: Programming Language :: Python :: 3.9
Classifier: Programming Language :: Python :: 3.10
Classifier: Programming Language :: Python :: 3.11
Classifier: Programming Language :: Python :: 3.12
Classifier: Topic :: Scientific/Engineering :: GIS
Classifier: Topic :: Scientific/Engineering :: Hydrology
Requires-Python: >=3.9
License-File: LICENSE
Requires-Dist: numpy>=1.20.0
Requires-Dist: rasterio>=1.3.0
Provides-Extra: dev
Requires-Dist: pytest>=7.0.0; extra == "dev"
Requires-Dist: pytest-cov>=4.0.0; extra == "dev"
Requires-Dist: ruff>=0.1.0; extra == "dev"
Provides-Extra: gee
Requires-Dist: earthengine-api>=0.1.300; extra == "gee"
Requires-Dist: geemap>=0.20.0; extra == "gee"
Provides-Extra: ndvi2gif
Requires-Dist: ndvi2gif>=0.0.6; extra == "ndvi2gif"
Provides-Extra: all
Requires-Dist: phydroperiod[dev,gee,ndvi2gif]; extra == "all"
Dynamic: license-file
